Workbook

Sheet DCF
C2: Historicals | F2: Forecasts | L2: Gordon Growth Method
B3: In USD millions | C3: 2023 | D3: =C3+1 | E3: =D3+1 | F3: =E3+1 | G3: =F3+1 | H3: =G3+1 | I3: =H3+1 | J3: =I3+1 | L3: Terminal-Year UFCF (normalized) | M3: =J4*M6
B4: Total Revenue | C4: ='Revenue Build'!C9 | D4: ='Revenue Build'!D9 | E4: ='Revenue Build'!E9 | F4: ='Revenue Build'!F9 | G4: ='Revenue Build'!G9 | H4: ='Revenue Build'!H9 | I4: ='Revenue Build'!I9 | J4: ='Revenue Build'!J9 | L4: Perpetuity Growth Rate | M4: 0.03
B5: % Growth | D5: =D4/C4-1 | E5: =E4/D4-1 | F5: =F4/E4-1 | G5: =G4/F4-1 | H5: =H4/G4-1 | I5: =I4/H4-1 | J5: =J4/I4-1 | L5: TV FCF | M5: =M3*(1+M4)
B6: COGS | C6: ='Annual IS'!B9 | D6: ='Annual IS'!C9 | E6: ='Annual IS'!D9 | F6: =F4*F32 | G6: =G4*G32 | H6: =H4*H32 | I6: =I4*I32 | J6: =J4*J32 | L6: Terminal UFCF Margin (normalized) | M6: 0.1
B7: Gross profit | C7: =C4-C6 | D7: =D4-D6 | E7: =E4-E6 | F7: =F4-F6 | G7: =G4-G6 | H7: =H4-H6 | I7: =I4-I6 | J7: =J4-J6 | L7: TV | M7: =M5/('WACC Calculations'!C13-M4)
B8: Gross Profit Margin | C8: =C7/C4 | D8: =D7/D4 | E8: =E7/E4 | F8: =F7/F4 | G8: =G7/G4 | H8: =H7/H4 | I8: =I7/I4 | J8: =J7/J4
B9: Hour-driven G&A (insurance, support) | C9: ='Revenue Build'!C5*C33 | D9: ='Revenue Build'!D5*D33 | E9: ='Revenue Build'!E5*E33 | F9: ='Revenue Build'!F5*F33 | G9: ='Revenue Build'!G5*G33 | H9: ='Revenue Build'!H5*H33 | I9: ='Revenue Build'!I5*I33 | J9: ='Revenue Build'!J5*J33 | L9: PV of TV | M9: =M7/(1+F24)^(F23+4)
B10: Fixed opex (other G&A, S&M, R&D) | C10: ='Annual IS'!B17-C9-C11 | D10: ='Annual IS'!C17-D9-D11 | E10: ='Annual IS'!D17-E9-E11 | F10: =E10*(1+F34) | G10: =F10*(1+G34) | H10: =G10*(1+H34) | I10: =H10*(1+I34) | J10: =I10*(1+J34) | L10: PV of FCF | M10: =SUM(F28:J28)
B11: Stock-based comp (in opex) | C11: ='Annual IS'!B93-'Annual IS'!B89 | D11: ='Annual IS'!C93-'Annual IS'!C89 | E11: ='Annual IS'!D93-'Annual IS'!D89 | F11: =F4*F35 | G11: =G4*G35 | H11: =H4*H35 | I11: =I4*I35 | J11: =J4*J35
B12: OpEx | C12: =SUM(C9:C11) | D12: =SUM(D9:D11) | E12: =SUM(E9:E11) | F12: =SUM(F9:F11) | G12: =SUM(G9:G11) | H12: =SUM(H9:H11) | I12: =SUM(I9:I11) | J12: =SUM(J9:J11) | L12: Implied EV | M12: =M10+M9
B13: EBIT | C13: =C7-C12 | D13: =D7-D12 | E13: =E7-E12 | F13: =F7-F12 | G13: =G7-G12 | H13: =H7-H12 | I13: =I7-I12 | J13: =J7-J12
B14: EBIT Margin | C14: =C13/C4 | D14: =D13/D4 | E14: =E13/E4 | F14: =F13/F4 | G14: =G13/G4 | H14: =H13/H4 | I14: =I13/I4 | J14: =J13/J4 | L14: (+) Cash | M14: ='Key Stats'!B63
B15: (-) Income Tax Expense | C15: ='Annual IS'!B33 | D15: ='Annual IS'!C33 | E15: ='Annual IS'!D33 | F15: =MAX(F13,0)*F36 | G15: =MAX(G13,0)*G36 | H15: =MAX(H13,0)*H36 | I15: =MAX(I13,0)*I36 | J15: =MAX(J13,0)*J36 | L15: (-) Debt | M15: 0
B16: NOPAT | C16: =C13-C15 | D16: =D13-D15 | E16: =E13-E15 | F16: =F13-F15 | G16: =G13-G15 | H16: =H13-H15 | I16: =I13-I15 | J16: =J13-J15 | L16: Implied Equity Value | M16: =M12+M14-M15
B17: (+) D&A | C17: 8.02 | D17: 9.126 | E17: 8.529 | F17: =F4*F37 | G17: =G4*G37 | H17: =H4*H37 | I17: =I4*I37 | J17: =J4*J37
B18: (+) SBC (historical only) | C18: ='Annual IS'!B93 | D18: ='Annual IS'!C93 | E18: ='Annual IS'!D93 | F18: 0 | G18: 0 | H18: 0 | I18: 0 | J18: 0 | L18: Shares Outstanding | M18: ='WACC Calculations'!C27
B19: (-) Changes in NWC | C19: -0.095 | D19: -15.22 | E19: 3.355 | F19: =F4*F38 | G19: =G4*G38 | H19: =H4*H38 | I19: =I4*I38 | J19: =J4*J38
B20: (-) CapEx | C20: -4.802 | D20: -4.451 | E20: -5.914 | F20: =-F4*F39 | G20: =-G4*G39 | H20: =-H4*H39 | I20: =-I4*I39 | J20: =-J4*J39 | L20: Implied Stock Price | M20: =M16/M18
B21: UFCF | C21: =SUM(C16:C20) | D21: =SUM(D16:D20) | E21: =SUM(E16:E20) | F21: =SUM(F16:F20) | G21: =SUM(G16:G20) | H21: =SUM(H16:H20) | I21: =SUM(I16:I20) | J21: =SUM(J16:J20) | L21: Current Stock Price | M21: ='WACC Calculations'!C15
B22: UFCF Margin | C22: =C21/C4 | D22: =D21/D4 | E22: =E21/E4 | F22: =F21/F4 | G22: =G21/G4 | H22: =H21/H4 | I22: =I21/I4 | J22: =J21/J4 | L22: Implied Upside/(Downside) | M22: =M20/M21-1
B23: Stub Period Fraction | F23: =(DATE(F$3,12,31)-$M$23)/365 | G23: 1 | H23: 1 | I23: 1 | J23: 1 | L23: Valuation Date | M23: =DATE(2026,9,10)
B24: WACC | F24: ='WACC Calculations'!$C$13 | G24: =F24 | H24: =G24 | I24: =H24 | J24: =I24
B25: Discount Period | F25: =F23/2 | G25: =F23+0.5 | H25: =G25+1 | I25: =H25+1 | J25: =I25+1 | L25: Exit Multiple Method
B26: Discount Factor | F26: =(1+F24)^F25 | G26: =(1+G24)^G25 | H26: =(1+H24)^H25 | I26: =(1+I24)^I25 | J26: =(1+J24)^J25 | L26: Last Year Revenue | M26: =J4
B27: UFCF Counted (x Stub Fraction) | F27: =F21*F23 | G27: =G21*G23 | H27: =H21*H23 | I27: =I21*I23 | J27: =J21*J23 | L27: Terminal EV/Revenue Multiple | M27: 2.5
B28: NPV of UFCF | F28: =F27/F26 | G28: =G27/G26 | H28: =H27/H26 | I28: =I27/I26 | J28: =J27/J26 | L28: TV | M28: =M27*M26
B29: Diluted Shares Outstanding (mm) | C29: ='Annual IS'!B55 | D29: ='Annual IS'!C55 | E29: ='Annual IS'!D55 | F29: ='WACC Calculations'!C27*(1+F40) | G29: =F29*(1+G40) | H29: =G29*(1+H40) | I29: =H29*(1+I40) | J29: =I29*(1+J40)
L30: PV of TV | M30: =M28/(1+F24)^(F23+4)
B31: Drivers | L31: PV of FCF | M31: =SUM(F28:J28)
B32: COGS as a % of Revenue | C32: =C6/C4 | D32: =D6/D4 | E32: =E6/E4 | F32: =1-'Revenue Build'!F31 | G32: =1-'Revenue Build'!G31 | H32: =1-'Revenue Build'!H31 | I32: =1-'Revenue Build'!I31 | J32: =1-'Revenue Build'!J31 | L32: Implied EV | M32: =M31+M30
B33: Hour-driven G&A (% of services revenue) | C33: 0.065 | D33: 0.065 | E33: 0.065 | F33: 0.065 | G33: 0.065 | H33: 0.065 | I33: 0.065 | J33: 0.065
B34: Fixed opex growth | D34: =D10/C10-1 | E34: =E10/D10-1 | F34: 0.08 | G34: 0.04 | H34: 0.04 | I34: 0.04 | J34: 0.04 | L34: (+) Cash | M34: =M14
B35: SBC as a % of Revenue | C35: =C11/C4 | D35: =D11/D4 | E35: =E11/E4 | F35: 0.12 | G35: 0.1 | H35: 0.08 | I35: 0.07 | J35: 0.06 | L35: (-) Debt | M35: =M15
B36: Effective Tax Rate | C36: =IF(C13>0,C15/C13,0) | D36: =IF(D13>0,D15/D13,0) | E36: =IF(E13>0,E15/E13,0) | F36: 0.21 | G36: 0.21 | H36: 0.21 | I36: 0.21 | J36: 0.21 | L36: Implied Equity Value | M36: =M32+M34-M35
B37: D&A as a % of Revenue | C37: =C17/C4 | D37: =D17/D4 | E37: =E17/E4 | F37: 0.018 | G37: 0.018 | H37: 0.018 | I37: 0.018 | J37: 0.018
B38: Changes in NWC as a % of Revenue | C38: =C19/C4 | D38: =D19/D4 | E38: =E19/E4 | F38: -0.015 | G38: -0.015 | H38: -0.015 | I38: -0.015 | J38: -0.015 | L38: Shares Outstanding | M38: =M18
B39: Capex as a % of Revenue | C39: =-C20/C4 | D39: =-D20/D4 | E39: =-E20/E4 | F39: 0.014 | G39: 0.014 | H39: 0.014 | I39: 0.014 | J39: 0.014
B40: Diluted Share Count Growth | F40: 0.025 | G40: 0.025 | H40: 0.025 | I40: 0.025 | J40: 0.025 | L40: Implied Stock Price | M40: =M36/M38
L41: Current Stock Price | M41: =M21
L42: Implied Upside/(Downside) | M42: =M40/M41-1
L45: Blended Share Price Calculations
L46: Gordon Growth Method | M46: =M20
L47: Exit Multiple Method | M47: =M40
L48: Blended Share Price Target | M48: =AVERAGE(M46:M47)
L49: Implied Upside/(Downside) | M49: =M48/M41-1

Sheet Revenue Build
C2: Historicals | F2: Forecasts
B3: Revenue ($ millions) | C3: 2023 | D3: =C3+1 | E3: =D3+1 | F3: =E3+1 | G3: =F3+1 | H3: =G3+1 | I3: =H3+1 | J3: =I3+1
B4: Software (platform) | C4: 57.9 | D4: 78.6 | E4: 101.1 | F4: =E4*(1+F19) | G4: =F4*(1+G19) | H4: =G4*(1+H19) | I4: =H4*(1+I19) | J4: =I4*(1+J19)
B5: Services | C5: =C6+C7 | D5: =D6+D7 | E5: =E6+E7 | F5: =F6+F7 | G5: =G6+G7 | H5: =H6+H7 | I5: =I6+I7 | J5: =J6+J7
B6: Microtransit & paratransit | C6: =C9-C8-C4-C7 | D6: =D9-D8-D4-D7 | E6: =E9-E8-E4-E7 | F6: =E6*(1+F20) | G6: =F6*(1+G20) | H6: =G6*(1+H20) | I6: =H6*(1+I20) | J6: =I6*(1+J20)
B7: Network deals | C7: 0 | D7: 11.1 | E7: 14.4 | F7: =E22+0.5*F21 | G7: =F22+0.5*G21 | H7: =G22+0.5*H21 | I7: =H22+0.5*I21 | J7: =I22+0.5*J21
B8: One-time (implementation, consulting) | C8: =C9*C23 | D8: =D9*D23 | E8: =E9*E23 | F8: =(F4+F5)*F23/(1-F23) | G8: =(G4+G5)*G23/(1-G23) | H8: =(H4+H5)*H23/(1-H23) | I8: =(I4+I5)*I23/(1-I23) | J8: =(J4+J5)*J23/(1-J23)
B9: Total net revenue | C9: ='Annual IS'!B7 | D9: ='Annual IS'!C7 | E9: ='Annual IS'!D7 | F9: =F4+F5+F8 | G9: =G4+G5+G8 | H9: =H4+H5+H8 | I9: =I4+I5+I8 | J9: =J4+J5+J8
B10: % growth | D10: =D9/C9-1 | E10: =E9/D9-1 | F10: =F9/E9-1 | G10: =G9/F9-1 | H10: =H9/G9-1 | I10: =I9/H9-1 | J10: =J9/I9-1
B11: Consensus | C11: =C9 | D11: =D9 | E11: =E9 | F11: ='Consensus (BBG)'!P7 | G11: ='Consensus (BBG)'!Q7 | H11: ='Key Stats'!H16
B12: % growth | D12: =D11/C11-1 | E12: =E11/D11-1 | F12: =F11/E11-1 | G12: =G11/F11-1 | H12: =H11/G11-1
B13: Model vs consensus | F13: =F9/F11-1 | G13: =G9/G11-1 | H13: =H9/H11-1
B14: Services % of revenue | C14: =C5/C9 | D14: =D5/D9 | E14: =E5/E9 | F14: =F5/F9 | G14: =G5/G9 | H14: =H5/H9 | I14: =I5/I9 | J14: =J5/J9
B15: Network deals % of revenue | C15: =C7/C9 | D15: =D7/D9 | E15: =E7/E9 | F15: =F7/F9 | G15: =G7/G9 | H15: =H7/H9 | I15: =I7/I9 | J15: =J7/J9
B16: Network deals share of revenue growth | D16: =(D7-C7)/(D9-C9) | E16: =(E7-D7)/(E9-D9) | F16: =(F7-E7)/(F9-E9) | G16: =(G7-F7)/(G9-F9) | H16: =(H7-G7)/(H9-G9) | I16: =(I7-H7)/(I9-H9) | J16: =(J7-I7)/(J9-I9)
B18: DRIVERS
B19: Software revenue % growth | D19: =D4/C4-1 | E19: =E4/D4-1 | F19: 0.12 | G19: 0.11 | H19: 0.1 | I19: 0.09 | J19: 0.08
B20: Microtransit & paratransit % growth | D20: =D6/C6-1 | E20: =E6/D6-1 | F20: 0.25 | G20: 0.16 | H20: 0.12 | I20: 0.1 | J20: 0.08
B21: Network: new contract value launched ($mm) | D21: =D22-C22 | E21: =E22-D22 | F21: 20 | G21: 40 | H21: 60 | I21: 70 | J21: 80
B22: Network: contract run-rate, year-end ($mm) | C22: 0 | D22: 11.1 | E22: 23.5 | F22: =E22+F21 | G22: =F22+G21 | H22: =G22+H21 | I22: =H22+I21 | J22: =I22+J21
B23: One-time revenue % of total | C23: 0.03 | D23: 0.03 | E23: 0.03 | F23: 0.03 | G23: 0.03 | H23: 0.03 | I23: 0.03 | J23: 0.03
B25: GROSS MARGIN BY STREAM
B26: Software | F26: 0.75 | G26: 0.75 | H26: 0.75 | I26: 0.75 | J26: 0.75
B27: Microtransit & paratransit | F27: 0.293 | G27: 0.293 | H27: 0.293 | I27: 0.293 | J27: 0.293
B28: Network deals | F28: 0.25 | G28: 0.25 | H28: 0.25 | I28: 0.25 | J28: 0.25
B29: One-time | F29: 0.75 | G29: 0.75 | H29: 0.75 | I29: 0.75 | J29: 0.75
B30: Gross profit ($mm) | C30: ='Annual IS'!B10 | D30: ='Annual IS'!C10 | E30: ='Annual IS'!D10 | F30: =F4*F26+F6*F27+F7*F28+F8*F29 | G30: =G4*G26+G6*G27+G7*G28+G8*G29 | H30: =H4*H26+H6*H27+H7*H28+H8*H29 | I30: =I4*I26+I6*I27+I7*I28+I8*I29 | J30: =J4*J26+J6*J27+J7*J28+J8*J29
B31: Gross margin | C31: =C30/C9 | D31: =D30/D9 | E31: =E30/E9 | F31: =F30/F9 | G31: =G30/G9 | H31: =H30/H9 | I31: =I30/I9 | J31: =J30/J9
B32: Consensus gross margin | C32: =C31 | D32: =D31 | E32: =E31 | F32: ='Consensus (BBG)'!P23 | G32: ='Consensus (BBG)'!Q23 | H32: ='Key Stats'!H20

Sheet WACC Calculations
B2: WACC Calculations
B3: Debt | C3: /
B4: Equity | C4: =C17
B5: % Debt | C5: 0
B6: % Equity | C6: 1
B7: Cost of Debt | C7: /
B8: After-Tax Cost of Debt | C8: /
B9: Cost of Equity | C9: =C10+(C11*C12)
B10: US 10Y Treasury Yield | C10: 0.0483
B11: Beta | C11: 1.03
B12: Market Risk Premium | C12: 0.0446
B13: WACC | C13: =C9
B15: Share Price ($) | C15: 29.98
B16: Shares Oustanding (mm) | C16: ='Key Stats'!B51
B17: Market Cap (mm) | C17: =C15*C16
B20: Diluted Shares
B21: Basic shares outstanding (mm) | C21: =C16
B22: Options outstanding (mm) | C22: 8.901695
B23: Weighted-avg. exercise price ($) | C23: 13.94
B24: Net shares from options (mm) | C24: =C22*MAX(0,1-C23/C15)
B25: Unvested RSUs (mm) | C25: 3.750862
B26: PSUs | C26: 0
B27: Diluted Shares Outstanding (mm) | C27: =C21+C24+C25+C26

Sheet Supporting Tabs >>>

Sheet Consensus (BBG)
A1: Via Transportation Inc- Company Financial (Multiple Periods) | P1: Source: Bloomberg consensus (VIA US Equity), quarterly. FY columns sum the four quarters (FY26 includes Q1-Q2 2026 actuals).
A2: VIA US Equity Periodicity:Q Currency:USD Estimate Source:BST Actual Source:Bloomberg
A3: In Millions of USD | E3: 2025 Q3 (Rep) | F3: 2025 Q4 (Rep) | G3: 2026 Q1 (Rep) | H3: 2026 Q2 (Rep) | I3: 2026 Q3 (Fwd) | J3: 2026 Q4 (Fwd) | K3: 2027 Q1 (Fwd) | L3: 2027 Q2 (Fwd) | M3: 2027 Q3 (Fwd) | N3: 2027 Q4 (Fwd) | P3: FY2026E | Q3: FY2027E
A4: 3 Months Ending | B4: Field Expression | C4: Calcrt Field | D4: Segment Id | E4: 45930 | F4: 46022 | G4: 46112 | H4: 46203 | I4: 46295 | J4: 46387 | K4: 46477 | L4: 46568 | M4: 46660 | N4: 46752 | P4: Sum of Q1-Q4 | Q4: Sum of Q1-Q4
A5: Highlights
A6: Adjusted Diluted EPS | B6: IS_COMP_EPS_ADJUSTED_OLD | C6: IS900 | E6: -0.127926 | F6: -0.05921 | G6: -0.05 | H6: -0.010282 | I6: -0.0272 | J6: 0.0473 | K6: 0.0558 | L6: 0.0971 | M6: 0.1083 | N6: 0.1539
A7: Revenue | B7: IS_COMP_SALES | C7: IS902 | E7: 109.653 | F7: 118.909 | G7: 127.434 | H7: 135.707 | I7: 138 | J7: 150.55556 | K7: 156.66667 | L7: 167.44444 | M7: 169.11111 | N7: 181.55556 | P7: =SUM(G7:J7) | Q7: =SUM(K7:N7)
A9: Operating Income | B9: IS_COMPARABLE_EBIT | C9: IM132 | E9: -18.891 | F9: -24.391 | G9: -23.584 | H9: -21.754 | I9: -21.525 | J9: -15.75 | K9: -14.66125 | L9: -11.1575 | M9: -10.58375 | N9: -7.3075
A10: Adjusted EBITDA | B10: IS_COMPARABLE_EBITDA | C10: IM131 | E10: -8.692 | F10: -7.384 | G10: -5.809 | H10: -0.003441 | I10: -4.0322222 | J10: 2.4097778 | K10: 3.4154444 | L10: 6.9811111 | M10: 7.79 | N10: 11.256667 | P10: =SUM(G10:J10) | Q10: =SUM(K10:N10)
A11: Adjusted Net Income | B11: IS_COMP_NET_INCOME_ADJUST_OLD | C11: IS903 | E11: -9.684 | F11: -4.796 | G11: -3.771 | H11: -0.838 | I11: -4.1111111 | J11: 2.1888889 | K11: 3.2643333 | L11: 7.1233333 | M11: 7.9644444 | N11: 11.425556
A13: Business Breakdown
A14: Customer Count | B14: NUMBER_OF_CUSTOMERS | C14: M6307 | D14: SEG6561238188 Segment | G14: 0.838 | H14: 0.847 | I14: 0.862 | J14: 0.888 | K14: 0.909 | L14: 0.923 | M14: 0.94 | N14: 0.962
A16: Platform Annual Run-Rate Revenue | B16: SALES_REV_TURN | C16: IS010 | D16: SEG9057071857 Segment | E16: 109.653 | G16: 509.736 | H16: 542.828
A18: Income Statement
A19: Total Revenue | B19: IS_COMP_SALES | C19: IS902 | E19: 109.653 | F19: 118.909 | G19: 127.434 | H19: 135.707 | I19: 138 | J19: 150.55556 | K19: 156.66667 | L19: 167.44444 | M19: 169.11111 | N19: 181.55556
A21: Cost of Revenue | B21: IS_COGS_TO_FE_AND_PP_AND_G | C21: IS021 | E21: 66.567 | F21: 71.956 | G21: 77.379 | H21: 80.101 | I21: 83.211666 | J21: 90.352505 | K21: 93.624765 | L21: 99.293944 | M21: 99.948153 | N21: 106.55178
A22: Gross Profit | B22: CB_IS_GROSS_PROFIT | C22: IC399 | E22: 43.086 | F22: 46.953 | G22: 50.055 | H22: 55.606 | I22: 54.725621 | J22: 60.265998 | K22: 63.131057 | L22: 68.097072 | M22: 69.145007 | N22: 75.005961 | P22: =SUM(G22:J22) | Q22: =SUM(K22:N22)
A23: Gross Margin (%) | B23: IS_COMP_GROSS_MARGIN_PERCENTAGE | C23: IM092 | E23: 40 | F23: 39.86578 | G23: 40 | H23: 41 | I23: 39.814126 | J23: 40.144826 | K23: 40.373965 | L23: 40.750632 | M23: 40.962324 | N23: 41.37826 | P23: =P22/P7 | Q23: =Q22/Q7
A25: Total Operating Expenses | B25: IS_OPERATING_EXPN | C25: IS032 | E25: 61.977 | F25: 71.344 | G25: 73.639 | H25: 77.36 | I25: 75.877208 | J25: 76.113875 | K25: 76.702573 | L25: 78.26794 | M25: 78.316136 | N25: 81.6391
A26: As % of Revenue | B26: OPERATING_EXPENSES_TO_NET_SALES | C26: RR280 | E26: 56.521025 | F26: 59.998823 | G26: 57.785991 | H26: 57.005166 | I26: 54.688393 | J26: 51.535505 | K26: 51.096447 | L26: 49.024018 | M26: 48.388347 | N26: 46.402614
A27: Research & Development | B27: IS_OPEX_R_AND_D_GAAP | C27: IM441 | E27: 23.131 | F27: 25.138 | G27: 24.528 | H27: 26.108 | I27: 25.943142 | J27: 25.936699 | K27: 26.175263 | L27: 26.843024 | M27: 26.852701 | N27: 28.081873
A28: As % of Revenue | B28: RD_EXPEND_TO_NET_SALES | C28: RR295 | E28: 21.094726 | F28: 21.140536 | G28: 19.247611 | H28: 19.238506 | I28: 18.900946 | J28: 17.337263 | K28: 17.025867 | L28: 16.342758 | M28: 16.145862 | N28: 15.839969
A29: Sales & Marketing | B29: CB_IS_S_AND_M_EXPENSE | C29: IM736 | E29: 17.657 | F29: 18.591 | G29: 20.49 | H29: 21.142 | I29: 20.405977 | J29: 20.323802 | K29: 20.788773 | L29: 21.591884 | M29: 21.750266 | N29: 22.48428
A30: General & Administrative | B30: CB_IS_GENL_AND_ADMIN_EXPN | C30: IM737 | E30: 21.189 | F30: 27.615 | G30: 28.621 | H30: 30.11 | I30: 29.174292 | J30: 29.348421 | K30: 29.312821 | L30: 29.721998 | M30: 29.749285 | N30: 30.559738
A32: Depreciation & Amortization | B32: CF_DEPR_AMORT | C32: CF011 | E32: 2.133 | F32: 2.053 | G32: 2.399 | H32: 2.38 | I32: 2.5049788 | J32: 2.3744769 | K32: 1.86643 | L32: 1.6622628 | M32: 1.6626765 | N32: 1.7197502
A33: Amortization | B33: CB_IS_AMORT_INTANG_ASSET_ATTR_OP_EX | C33: IL286 | E33: 1.1 | F33: 1.1 | G33: 1.412 | H33: 1.38 | I33: 1.1289915 | J33: 1.1370473 | K33: 0.97398159 | L33: 0.76939823 | M33: 0.74977451 | N33: 0.75963067
A35: Operating Income | B35: IS_COMPARABLE_EBIT | C35: IM132 | E35: -18.891 | F35: -24.391 | G35: -23.584 | H35: -21.754 | I35: -21.525 | J35: -15.75 | K35: -14.66125 | L35: -11.1575 | M35: -10.58375 | N35: -7.3075
A36: Operating Margin (%) | B36: OPER_MARGIN | C36: RR026 | E36: -17.227983 | F36: -20.512325 | G36: -18.506835 | H36: -16.030124 | I36: -15.63721 | J36: -10.54657 | K36: -9.7129102 | L36: -6.8244943 | M36: -6.58398 | N36: -4.4346394
A38: EBITDA | B38: IS_COMPARABLE_EBITDA | C38: IM131 | E38: -8.692 | F38: -7.384 | G38: -5.809 | H38: -0.003441 | I38: -4.0322222 | J38: 2.4097778 | K38: 3.4154444 | L38: 6.9811111 | M38: 7.79 | N38: 11.256667
A40: Interest Expense (Income), Net | B40: IS_NET_INTEREST_EXPENSE | C40: IS325 | E40: 1.264 | F40: -2.964 | G40: -2.55 | H40: -2.517 | I40: -2.3281307 | J40: -2.3313999 | K40: -2.4416419 | L40: -2.4333148 | M40: -2.4498054 | N40: -2.5072543
... A54: Diluted EPS | B54: IS_COMP_EPS_GAAP | C54: IS901 | E54: -0.487279 | F54: -0.270815 | G54: -0.25 | H54: -0.24 | I54: -0.2425 | J54: -0.17 | K54: -0.15625 | L54: -0.1105 | M54: -0.101625 | N54: -0.06275
A56: Adjusted Results
A57: Net Income | B57: IS_COMP_NET_INCOME_ADJUST_OLD | C57: IS903 | E57: -9.684 | F57: -4.796 | G57: -3.771 | H57: -0.838 | I57: -4.1111111 | J57: 2.1888889 | K57: 3.2643333 | L57: 7.1233333 | M57: 7.9644444 | N57: 11.425556
A58: Diluted EPS | B58: IS_COMP_EPS_ADJUSTED_OLD | C58: IS900 | E58: -0.127926 | F58: -0.05921 | G58: -0.05 | H58: -0.010282 | I58: -0.0272 | J58: 0.0473 | K58: 0.0558 | L58: 0.0971 | M58: 0.1083 | N58: 0.1539
A60: Company Specific Adjustments
A61: Stock-Based Compensation | B61: CF_STOCK_BASED_COMPENSATION | C61: CF283 | E61: 6.592 | F61: 14.396 | G61: 15.564 | H61: 16.01 | I61: 15.580766 | J61: 16.159412 | K61: 15.935029 | L61: 16.110417 | M61: 16.225805 | N61: 16.543295
A62: Cost of Goods Sold | B62: IS_SBC_ATTRIB_TO_COGS_PRETX | C62: IM496 | E62: 0.038 | F62: 0.056 | G62: 0.075 | H62: 0.098 | I62: 0.093799452 | J62: 0.10061384 | K62: 0.10818837 | L62: 0.10898681 | M62: 0.10915316 | N62: 0.11168595
A63: Research & Development | B63: IS_SBC_ATTRIBUTABLE_TO_R_AND_D_PRETX | C63: IM494 | E63: 1.874 | F63: 3.54 | G63: 4.03 | H63: 4.302 | I63: 3.9572779 | J63: 3.9782008 | K63: 3.7168595 | L63: 3.744109 | M63: 3.796552 | N63: 3.909138
A64: Selling & Marketing | B64: IS_SBC_ATT_TO_S_AND_M_PRETX | C64: IM498 | E64: 1.687 | F64: 2.895 | G64: 3.328 | H64: 3.623 | I64: 3.1114576 | J64: 3.1286276 | K64: 3.191743 | L64: 3.2566368 | M64: 3.307942 | N64: 3.359073
A65: General & Administrative | B65: IS_SBC_ATT_TO_GENL_AND_ADMIN_PRETX | C65: IM497 | E65: 2.993 | F65: 7.905 | G65: 8.131 | H65: 7.987 | I65: 8.3911118 | J65: 8.9524793 | K65: 8.8966292 | L65: 8.9896109 | M65: 9.0190157 | N65: 9.1763904
A67: Condensed Balance Sheet
A68: Assets
A69: Current Assets | B69: BS_CUR_ASSET_REPORT | C69: BS015 | E69: 478.906 | F69: 469.551 | G69: 461.178 | H69: 458.206 | I69: 455.83193 | J69: 461.37135 | K69: 463.42964 | L69: 475.48974 | M69: 488.61609 | N69: 506.32026
A70: Accounts Receivable | B70: CB_BS_ACCOUNTS_RECEIVABLE | C70: BL309 | E70: 84.307 | F70: 81.572 | G70: 94.916 | H70: 104.679 | I70: 106.04096 | J70: 112.55409 | K70: 114.17026 | L70: 122.50116 | M70: 126.3323 | N70: 133.90622
A71: Prepaid Expenses | B71: PREPAID_EXPNSS_AND_OTHR | C71: BL249 | E71: 16.441 | F71: 17.065 | G71: 18.104 | H71: 17.612 | I71: 18.898151 | J71: 19.62686 | K71: 20.267057 | L71: 22.221437 | M71: 24.554103 | N71: 25.752775
A72: Non-Current Assets | B72: BS_TOTAL_NON_CURRENT_ASSETS | C72: BM321 | E72: 223.152 | F72: 263.544 | G72: 262.142 | H72: 260.143 | I72: 256.89528 | J72: 257.32459 | K72: 255.7249 | L72: 256.2449 | M72: 256.19117 | N72: 256.73704
A73: Property, Plant & Equipment | B73: CB_BS_PP_AND_E_NET | C73: BM788 | E73: 13.01 | F73: 13.395 | G73: 14.649 | H73: 16.051 | I73: 17.31801 | J73: 18.759023 | K73: 20.246377 | L73: 21.917724 | M73: 23.446563 | N73: 25.062908
A74: Operating Lease Right-of-Use Asset | B74: BS_OPER_LEA_RT_OF_USE_ASSETS | C74: BM659 | E74: 16.244 | F74: 18.319 | G74: 18.81 | H74: 17.085 | I74: 16.710429 | J74: 16.308 | K74: 15.905571 | L74: 15.503143 | M74: 15.100714 | N74: 14.698286
A75: Deferred Tax Assets | B75: BS_DEFERRED_TAX_ASSETS_LT | C75: BM079 | E75: 1.183 | F75: 0.529 | G75: 0.437 | H75: 0.401 | I75: 0.39987168 | J75: 0.40840824 | K75: 0.40882147 | L75: 0.41216304 | M75: 0.41392607 | N75: 0.42289395
A76: Intangible Assets | B76: CB_BS_INTANG_ASSETS_EX_GW_NT | C76: BM787 | E76: 24.127 | F76: 36.025 | G76: 34.336 | H76: 32.971 | I76: 30.172064 | J76: 29.41621 | K76: 28.048372 | L76: 27.472206 | M76: 26.564312 | N76: 25.834259
A77: Goodwill | B77: BS_GOODWILL | C77: BS161 | E77: 165.962 | F77: 192.305 | G77: 191.005 | H77: 190.72 | I77: 190.72 | J77: 190.72 | K77: 190.72 | L77: 190.72 | M77: 190.72 | N77: 190.72
A78: Other Assets | B78: CB_BS_OTHER_NONCURRENT_ASSETS | C78: BM784 | E78: 1.492 | F78: 1.8 | G78: 1.687 | H78: 1.614 | I78: 2.3182462 | J78: 2.4338655 | K78: 2.0103418 | L78: 2.0071481 | M78: 2.0265818 | N78: 2.1323269
A79: Total Assets | B79: BS_TOT_ASSET | C79: BS035 | E79: 702.058 | F79: 733.095 | G79: 723.32 | H79: 718.349 | I79: 713.71258 | J79: 719.49794 | K79: 720.63661 | L79: 733.12872 | M79: 746.3698 | N79: 764.5856
A81: Liabilities & Equity
A82: Current Liabilities | B82: CB_BS_CURR_LIABILITIES | C82: BL332 | E82: 92.705 | F82: 94.235 | G82: 90.624 | H82: 90.796 | I82: 91.609276 | J82: 96.585368 | K82: 93.357416 | L82: 96.155969 | M82: 98.925803 | N82: 103.97545
A83: Accounts Payable | B83: CB_BS_ACCOUNTS_PAYABLE | C83: BL370 | E83: 5.663 | F83: 4.427 | G83: 7.222 | H83: 6.039 | I83: 7.1553894 | J83: 7.4928034 | K83: 7.2221286 | L83: 7.3968202 | M83: 7.3845809 | N83: 7.7211873
A84: Accrued Expenses & Other Current Liabilities | B84: BS_ACCRUD_EXPNSS_AND_OTHR | C84: BL255 | E84: 25.838 | F84: 24.886 | G84: 21.128 | H84: 23.859 | I84: 24.747904 | J84: 24.810788 | K84: 24.143309 | L84: 24.652515 | M84: 26.072239 | N84: 27.633823
A85: Operating Lease Liabilities | B85: BS_ST_OPERATING_LEASE_LIABS | C85: BM660 | E85: 8.106 | F85: 9.749 | G85: 10.021 | H85: 9.829 | I85: 9.3560567 | J85: 9.6267906 | K85: 9.8153107 | L85: 10.658028 | M85: 10.90073 | N85: 11.240392
A86: Deferred Revenue | B86: CB_BS_ST_DEFER_REVENUE | C86: BL256 | E86: 24.103 | F86: 26.893 | G86: 23.954 | H86: 22.81 | I86: 23.971412 | J86: 25.253464 | K86: 23.730157 | L86: 23.247223 | M86: 24.874232 | N86: 25.582645
A87: Insurance Payables | B87: CB_BS_OTHER_CURRENT_LIABS | C87: BM786 | E87: 15.751 | F87: 15.144 | G87: 14.882 | H87: 15.329 | I87: 14.924238 | J87: 18.177354 | K87: 18.304416 | L87: 20.184078 | M87: 20.06668 | N87: 22.011254
A88: Accrued Compensation & Benefits | B88: BS_ST_ACC_CMPNSTN_POSTRET_OBLIG | C88: BL253 | E88: 13.244 | F88: 13.136 | G88: 13.417 | H88: 12.93 | I88: 11.048571 | J88: 11.313018 | K88: 10.105001 | L88: 10.289632 | M88: 9.8139796 | N88: 10.343274
A89: Non-Current Liabilities
A90: Operating Lease Liabilities | B90: BS_LT_OPERATING_LEASE_LIABS | C90: BM661 | E90: 8.409 | F90: 9.378 | G90: 9.249 | H90: 8.196 | I90: 9.1971428 | J90: 9.8048539 | K90: 10.04478 | L90: 10.45037 | M90: 10.76717 | N90: 11.339976
A91: Deferred Revenue | B91: CB_BS_LT_DEFERRED_REVENUE | C91: BL435 | E91: 1.354 | F91: 0 | G91: 1.321 | H91: 1.048 | I91: 1.5041025 | J91: 1.5825641 | K91: 1.446332 | L91: 1.4036236 | M91: 1.4769067 | N91: 1.5300728
A92: Total Liabilities | B92: BS_TOT_LIAB2 | C92: RR005 | E92: 127.468 | F92: 105.359 | G92: 101.194 | H92: 100.04 | I92: 104.11275 | J92: 108.34644 | K92: 105.22218 | L92: 108.38362 | M92: 111.54354 | N92: 117.21916
A93: Total Shareholders' Equity | B93: BS_TOT_EQY | C93: BS095 | E93: 574.59 | F93: 627.736 | G93: 622.126 | H93: 618.309 | I93: 609.59983 | J93: 611.1515 | K93: 615.41443 | L93: 624.74511 | M93: 634.82626 | N93: 647.36644
A94: Total Liabilities & Shareholders' Equity | B94: BS_TOT_ASSET | C94: BS035 | E94: 702.058 | F94: 733.095 | G94: 723.32 | H94: 718.349 | I94: 713.71258 | J94: 719.49794 | K94: 720.63661 | L94: 733.12872 | M94: 746.3698 | N94: 764.5856
A96: Condensed Cash Flow Statement
A97: Cash from Operating Activities
A98: Net Income | B98: IS_COMP_NET_INCOME_GAAP | C98: IS904 | E98: -36.887 | F98: -21.936 | G98: -20.149 | H98: -19.556 | I98: -19.7 | J98: -13.944444 | K98: -12.52 | L98: -8.6255556 | M98: -7.89 | N98: -4.7214444
A99: Depreciation & Amortization | B99: CF_DEPR_AMORT | C99: CF011 | E99: 2.133 | F99: 2.053 | G99: 2.399 | H99: 2.38 | I99: 2.5049788 | J99: 2.3744769 | K99: 1.86643 | L99: 1.6622628 | M99: 1.6626765 | N99: 1.7197502
A100: Stock-Based Compensation | B100: CF_STOCK_BASED_COMPENSATION | C100: CF283 | E100: 6.592 | F100: 14.396 | G100: 15.564 | H100: 16.01 | I100: 15.580766 | J100: 16.159412 | K100: 15.935029 | L100: 16.110417 | M100: 16.225805 | N100: 16.543295
A101: Change in Working Capital
A102: Accounts Receivable | B102: CB_CF_CHANGE_IN_ACCOUNTS_RECEIVABLE | C102: CF505 | E102: -2.061 | F102: 6.615 | G102: -13.788 | H102: -9.853 | I102: -1.3619626 | J102: -6.5131237 | K102: -1.6161749 | L102: -8.3309014 | M102: -3.8311407 | N102: -7.5739178
A103: Prepaid Expenses & Other Assets | B103: CF_CHANGE_IN_OTHR_CURRNT_ASSTS | C103: CF447 | E103: -1.305 | F103: -2.058 | G103: -1.003 | H103: 0.562 | I103: -2.5853585 | J103: -2.1087023 | K103: -0.92950752 | L103: -2.887083 | M103: -3.8278699 | N103: -2.2484927
A104: Accounts Payable | B104: CF_CHANGE_IN_ACCOUNTS_PAYABLE | C104: CF278 | E104: -1.253 | F104: -1.891 | G104: 2.818 | H104: -1.178 | I104: 1.1599062 | J104: 0.53985459 | K104: -0.38698913 | L104: -0.15624545 | M104: 0.19403502 | N104: 0.45679774
A105: Operating Lease Liabilities | B105: CF_CHANGE_IN_OPER_LEASE_LIBLTS | C105: CF440 | E105: -2.367 | F105: -1.92 | G105: -3.557 | H105: -2.296 | I105: -1.0771224 | J105: -0.38226396 | K105: -1.1185558 | L105: 0.052536663 | M105: -0.9182908 | N105: -0.60550551
A106: Deferred Revenue | B106: CF_CHG_IN_DEFER_UNEARND_REV_ST | C106: CF434 | E106: 2.672 | F106: 0.272 | G106: -3.233 | H106: -1.374 | I106: 1.5899525 | J106: 0.98577003 | K106: -1.3645358 | L106: -0.66635885 | M106: 1.662015 | N106: 0.41472139
A107: Accrued Compensation & Benefits | B107: CF_CHG_IN_ACC_CMPNSTN_PYRL_EXPNS | C107: CF452 | E107: 3.148 | F107: -0.299 | G107: 0.382 | H107: -0.47 | I107: 0.4764491 | J107: 0.8170164 | K107: -1.8104421 | L107: 0.29826853 | M107: -0.21669473 | N107: 1.0735502
A108: Cash Flow from Operations | B108: CB_CF_NET_CASH_OPERATING_ACT | C108: CF376 | E108: -8.53 | F108: -0.455 | G108: -21.197 | H108: -10.645 | I108: -1.3614234 | J108: 3.9030796 | K108: 1.3824495 | L108: 3.9147979 | M108: 8.5715683 | N108: 13.655872
A110: Cash from Investing Activities
A111: Capital Expenditures | B111: HEADLINE_CAPEX | C111: F1705 | E111: -0.354 | F111: -0.326 | G111: -0.289 | H111: -0.389 | I111: -1.154 | J111: -1.2465 | K111: -1.257 | L111: -1.3075 | M111: -1.315 | N111: -1.4055
A112: Acquisitions—Net of Cash Acquired | B112: CB_CF_OTHER_INVESTING_ACTIVITIES | C112: CF491 | F112: -39.892 | G112: 0 | H112: 0.279 | I112: -7.515 | J112: -14.157 | K112: -15 | L112: -15 | M112: -7.505 | N112: -16.367667
A113: Cash Flow from Investing | B113: CB_CF_NET_CASH_INVESTING_ACT | C113: CF377 | E113: -1.458 | F113: -41.247 | G113: -2.281 | H113: -2.125 | I113: -3.3646466 | J113: -5.4204759 | K113: -3.9773619 | L113: -4.068754 | M113: -4.0864929 | N113: -6.0895921
A115: Cash from Financing Activities
A116: Proceeds from Exercise of Stock Options | B116: CB_CF_EXERCISE_OF_STOCK_OPTIONS | C116: CF467 | E116: 7.898 | F116: 3.794 | G116: 0.996 | H116: 0.695 | I116: 2.1560417 | J116: 2.0277083 | K116: 2.0960833 | L116: 2.0932917 | M116: 2.4751389 | N116: 2.3081944
A117: Cash Flow from Financing | B117: CB_CF_NET_CASH_FINANCING_ACT | C117: CF378 | E117: 309.718 | F117: 34.376 | G117: 0.996 | H117: 0.695 | I117: -0.46452381 | J117: -0.61119048 | K117: 2.3240952 | L117: 2.3209048 | M117: 2.7573016 | N117: 2.4236508
A119: Special Company Reference Items
A120: Effect of Foreign Exchange Rates | B120: CF_EFFECT_FOREIGN_EXCHANGES | C120: CF291 | E120: 0.261 | F120: 0.119 | G120: -0.227 | H120: -0.085 | I120: -0.312 | J120: -0.312
A121: Net Change in Cash | B121: CB_CF_NET_CHANGE_IN_CASH | C121: CF475 | E121: 299.991 | F121: -7.207 | G121: -22.709 | H121: -12.16 | I121: -5.5983281 | J121: -1.7024143 | K121: -0.19807783 | L121: 1.7748184 | M121: 6.9625413 | N121: 8.9315825
A122: Cash & Cash Equivalents (BOP) | B122: CF_CASH_AND_CASH_EQUIV_BEG_BAL | C122: CF224 | E122: 79.301 | F122: 379.292 | G122: 372.085 | H122: 349.376 | I122: 337.21679 | J122: 331.61846 | K122: 329.91604 | L122: 330.34055 | M122: 330.62619 | N122: 336.65871
A123: Cash & Cash Equivalents (EOP) | B123: CF_CASH_AND_CASH_EQUIV_END_BAL | C123: CF227 | E123: 78.989 | F123: 372.085 | G123: 349.376 | H123: 337.216 | I123: 331.07946 | J123: 329.37704 | K123: 329.17897 | L123: 330.95378 | M123: 337.91633 | N123: 346.84791
A125: Free Cash Flow Margin (%) | B125: FREE_CASH_FLOW_MARGIN | C125: RX588 | E125: -8.1019215 | F125: -0.65680478 | G125: -16.860492 | H125: -8.1307523 | I125: -2.260492 | J125: 0.26923774 | K125: -0.46009561 | L125: 1.2680156 | M125: 3.8802903 | N125: 6.6193274
A126: CFO to Sales (%) | B126: CFO_TO_SALES | C126: RR139 | E126: -7.7790849 | F126: -0.38264555 | G126: -16.633708 | H126: -7.8441053 | I126: -0.60433934 | J126: 4.0360359 | K126: 3.1461816 | L126: 2.4692308 | M126: 4.980133 | N126: 8.8696344
A128: Source: Bloomberg

Sheet Annual IS
A1: Income Statement
A2: For the Fiscal Period Ending | B2: 12 months Dec-31-2023 | C2: 12 months Dec-31-2024 | D2: 12 months Dec-31-2025 | E2: LTM 12 months Jun-30-2026
A3: Currency | B3: USD | C3: USD | D3: USD | E3: USD
A5: Revenue | B5: 248.854 | C5: 337.63 | D5: 434.337 | E5: 491.703
A6: Other Revenue | B6: - | C6: - | D6: - | E6: -
A7: Total Revenue | B7: 248.854 | C7: 337.63 | D7: 434.337 | E7: 491.703
A9: Cost Of Goods Sold | B9: 149.446 | C9: 206.79 | D9: 262.534 | E9: 296
A10: Gross Profit | B10: 99.408 | C10: 130.84 | D10: 171.803 | E10: 195.703
A12: Selling General & Admin Exp. | B12: 118.03 | C12: 125.749 | D12: 155.205 | E12: 184.556
A13: R & D Exp. | B13: 95.833 | C13: 88.987 | D13: 92.303 | E13: 98.856
A14: Depreciation & Amort. | B14: - | C14: - | D14: - | E14: -
A15: Other Operating Expense/(Income) | B15: - | C15: - | D15: 0.911 | E15: 0.911
A17: Other Operating Exp., Total | B17: 213.863 | C17: 214.736 | D17: 248.419 | E17: 284.323
A19: Operating Income | B19: -114.5 | C19: -83.9 | D19: -76.6 | E19: -88.6
A21: Interest Expense | B21: -0.7 | C21: -4.3 | D21: -7.3 | E21: -3
A22: Interest and Invest. Income | B22: 3.599 | C22: 2.195 | D22: 5.272 | E22: 9.796
A23: Net Interest Exp. | B23: 2.946 | C23: -2.1 | D23: -2.1 | E23: 6.767
A25: Currency Exchange Gains (Loss) | B25: -1.5 | C25: 0.326 | D25: 0.475 | E25: -1.3
A26: Other Non-Operating Inc. (Exp.) | B26: -2.1 | C26: -4.9 | D26: -7.2 | E26: -5.2
A27: EBT Excl. Unusual Items | B27: -115.1 | C27: -90.5 | D27: -85.4 | E27: -88.4
A29: Impairment of Goodwill | B29: - | C29: - | D29: - | E29: -
A30: Other Unusual Items | B30: - | C30: 1.857 | D30: -8.5 | E30: -8.5
A31: EBT Incl. Unusual Items | B31: -115.1 | C31: -88.7 | D31: -93.8 | E31: -96.9
A33: Income Tax Expense | B33: 1.815 | C33: 1.89 | D33: 2.521 | E33: 1.599
A34: Earnings from Cont. Ops. | B34: -117 | C34: -90.6 | D34: -96.4 | E34: -98.5
A36: Earnings of Discontinued Ops. | B36: - | C36: - | D36: - | E36: -
A37: Extraord. Item & Account. Change | B37: - | C37: - | D37: - | E37: -
A38: Net Income to Company | B38: -117 | C38: -90.6 | D38: -96.4 | E38: -98.5
A40: Minority Int. in Earnings | B40: 0.278 | C40: 0.271 | D40: - | E40: -
A41: Net Income | B41: -116.7 | C41: -90.3 | D41: -96.4 | E41: -98.5
A43: Pref. Dividends and Other Adj. | B43: - | C43: - | D43: - | E43: -
A45: NI to Common Incl Extra Items | B45: -116.7 | C45: -90.3 | D45: -96.4 | E45: -98.5
A46: NI to Common Excl. Extra Items | B46: -116.7 | C46: -90.3 | D46: -96.4 | E46: -98.5
A48: Per Share Items
A49: Basic EPS | B49: -9.6 | C49: -7.21 | D49: -2.92 | E49: -1.47
A50: Basic EPS Excl. Extra Items | B50: -9.6 | C50: -7.21 | D50: -2.92 | E50: -1.47
A51: Weighted Avg. Basic Shares Out. | B51: 12.15567 | C51: 12.525706 | D51: 32.949511 | E51: 67.181601
A53: Diluted EPS | B53: -9.6 | C53: -7.21 | D53: -2.92 | E53: -1.47
A54: Diluted EPS Excl. Extra Items | B54: -9.6 | C54: -7.21 | D54: -2.92 | E54: -1.47
A55: Weighted Avg. Diluted Shares Out. | B55: 12.15567 | C55: 12.525706 | D55: 32.949511 | E55: 67.181601
A57: Normalized Basic EPS | B57: -5.9 | C57: -4.5 | D57: -1.62 | E57: -0.82
A58: Normalized Diluted EPS | B58: -5.9 | C58: -4.5 | D58: -1.62 | E58: -0.82
A60: Dividends per Share | B60: NA | C60: NA | D60: NA | E60: NA
A62: Supplemental Items
A63: EBITDA | B63: -106.4 | C63: -74.8 | D63: -68.1 | E63: -79.7
A64: EBITA | B64: -109.5 | C64: -78.3 | D64: -72 | E64: -83.6
A65: EBIT | B65: -114.5 | C65: -83.9 | D65: -76.6 | E65: -88.6
A66: EBITDAR | B66: -100.1 | C66: -65.9 | D66: -56.7 | E66: NA
A67: Effective Tax Rate % | B67: NM | C67: NM | D67: NM | E67: NM
A68: Current Domestic Taxes | B68: 0.148 | C68: 0.169 | D68: 0.243 | E68: 0.243
A69: Current Foreign Taxes | B69: 1.5 | C69: 1.499 | D69: 1.685 | E69: 1.685
A70: Total Current Taxes | B70: 1.648 | C70: 1.668 | D70: 1.928 | E70: 1.928
A71: Deferred Foreign Taxes | B71: 0.167 | C71: 0.222 | D71: 0.593 | E71: 0.593
A72: Total Deferred Taxes | B72: 0.167 | C72: 0.222 | D72: 0.593 | E72: 0.593
A74: Normalized Net Income | B74: -71.7 | C74: -56.3 | D74: -53.4 | E74: -55.3
A75: Interest on Long Term Debt | B75: NA | C75: 3.2 | D75: 4.6 | E75: NA
A76: Filing Date | B76: 46087 | C76: 46087 | D76: 46087 | E76: 46240
A77: Restatement Type | B77: NC | C77: NC | D77: O | E77: O
A78: Calculation Type | B78: REP | C78: REP | D78: REP | E78: LTM
A80: Supplemental Operating Expense Items
A81: Advertising Exp. | B81: 4.6 | C81: 5.2 | D81: 8.8 | E81: NA
A82: Selling and Marketing Exp. | B82: 53.799 | C82: 55.484 | D82: 67.204 | E82: 77.661
A83: General and Administrative Exp. | B83: 64.231 | C83: 70.265 | D83: 88.001 | E83: 106.895
A84: R&D Exp. | B84: 95.833 | C84: 88.987 | D84: 92.352 | E84: 98.905
A85: Net Rental Exp. | B85: 6.316 | C85: 8.866 | D85: 11.386 | E85: NA
A86: Imputed Oper. Lease Interest Exp. | B86: - | C86: 6.060656 | D86: 13.149282 | E86: -
A87: Imputed Oper. Lease Depreciation | B87: - | C87: 2.805344 | D87: -1.8 | E87: -
A89: Stock-Based Comp., COGS | B89: 0.185 | C89: 0.227 | D89: 0.2 | E89: 0.267
A90: Stock-Based Comp., R&D Exp. | B90: 4.959 | C90: 6.583 | D90: 8.577 | E90: 13.746
A91: Stock-Based Comp., S&M Exp. | B91: 3.134 | C91: 4.023 | D91: 7.121 | E91: 11.533
A92: Stock-Based Comp., G&A Exp. | B92: 4.848 | C92: 10.393 | D92: 14.443 | E92: 27.016
A93: Stock-Based Comp., Total | B93: 13.126 | C93: 21.226 | D93: 30.341 | E93: 52.562
A96: Note: For multiple class companies, per share items are primary class equivalent, and for foreign companies listed as primary ADRs, per share items are ADR-equivalent.

Sheet Key Stats
A5: Via Transportation, Inc. (NYSE:VIA) > Financials > Key Stats
A7: In Millions of the trading currency, except per share items. | B7: Currency: | C7: Trading Currency | E7: Conversion: | F7: Historical
B8: Order: | C8: Latest on Right | E8: Units: | F8: S&P Capital IQ (Default)
B9: Decimals: | C9: Capital IQ (Default) | E9: Dilution: | F9: Basic
A12: Key Financials¹
A13: For the Fiscal Period Ending | B13: 12 months Dec-31-2023A | C13: 12 months Dec-31-2024A | D13: 12 months Dec-31-2025A | E13: LTM² 12 months Jun-30-2026A | F13: 12 months† Dec-31-2026E | G13: 12 months Dec-31-2027E | H13: 12 months Dec-31-2028E
A14: Currency | B14: USD | C14: USD | D14: USD | E14: USD | F14: USD | G14: USD | H14: USD
A16: Total Revenue | B16: 248.854 | C16: 337.63 | D16: 434.337 | E16: 491.703 | F16: 551.73774 | G16: 674.03932 | H16: 814.01794
A17: Growth Over Prior Year | B17: NA | C17: 0.356739 | D17: 0.286428 | E17: 0.291328 | F17: 0.27029873 | G17: 0.22166615 | H17: 0.2076713
A19: Gross Profit | B19: 99.408 | C19: 130.84 | D19: 171.803 | E19: 195.703 | F19: - | G19: - | H19: -
A20: Margin % | B20: 0.399463 | C20: 0.387524 | D20: 0.395552 | E20: 0.39801 | F20: 0.403 | G20: 0.409875 | H20: 0.4195
A22: EBITDA | B22: -106.4 | C22: -74.8 | D22: -68.1 | E22: -79.7 | F22: -10.78 | G22: 30.0682 | H22: 67.45326
A23: Margin % | B23: -0.4277 | C23: -0.221455 | D23: -0.15676 | E23: -0.161998 | F23: - | G23: 0.04460897 | H23: 0.082864586
A25: EBIT | B25: -114.5 | C25: -83.9 | D25: -76.6 | E25: -88.6 | F25: -81.17 | G25: -45.42 | H25: -21.93
A26: Margin % | B26: -0.459928 | C26: -0.248485 | D26: -0.176397 | E26: -0.18023 | F26: - | G26: - | H26: -
A28: Earnings from Cont. Ops. | B28: -117 | C28: -90.6 | D28: -96.4 | E28: -98.5 | F28: - | G28: - | H28: -
A29: Margin % | B29: -0.47001 | C29: -0.268198 | D29: -0.221857 | E29: -0.200381 | F29: - | G29: - | H29: -
A31: Net Income | B31: -116.7 | C31: -90.3 | D31: -96.4 | E31: -98.5 | F31: -2.55 | G31: 37.93337 | H31: 73.18674
A32: Margin % | B32: -0.468893 | C32: -0.267396 | D32: -0.221857 | E32: -0.200381 | F32: -0.0046256941 | G32: 0.056277681 | H32: 0.089908018
A34: Diluted EPS Excl. Extra Items³ | B34: -9.6 | C34: -7.21 | D34: -2.92 | E34: -1.47 | F34: -0.03 | G34: 0.42981 | H34: 0.79631
A35: Growth Over Prior Year | B35: NA | C35: NM | D35: NM | E35: NM | F35: - | G35: - | H35: 0.85270236
A38: Currency | B38: USD | C38: USD | D38: USD | E38: USD | F38: USD | G38: USD | H38: USD
A39: Exchange Rate | B39: 1 | C39: 1 | D39: 1 | E39: 1 | F39: 1 | G39: 1 | H39: 1
A40: Conversion Method | B40: H | C40: H | D40: H | E40: H | F40: S | G40: S | H40: S
A42: ¹All results are taken from the most recently filed statement for each period. When there has been more than one, earlier filings can be viewed on the individual statement pages.
A43: ²Growth rates for the LTM period are calculated against the LTM period ending 12 months before.
A44: ³All forward period figures are consensus mean estimates provided by the brokers and may not be on a comparable basis as financials.
A45: †Growth rates for forward periods are calculated against prior period estimates or actual pro forma results as disclosed on the Estimates Consensus page.
A46: Growth Rates are calculated in originally reported currency only and will not reflect any currency conversion selected above.
A48: Current Capitalization (Millions of USD)
A49: Currency | B49: USD
A50: Share Price | B50: 27.98
A51: Shares Out. | B51: 81.505613
A53: Market Capitalization | B53: 2280.5271
A54: Class A Common Stock Shares Out | B54: 77.65943
A55: * Class A Common Stock Share Price | B55: 27.98
A56: = Class A Common Stock Market Capitalization | B56: 2172.9109
A57: + Class B Common Stock Shares Out | B57: 3.846183
A58: * Class B Common Stock Share Price | B58: 27.98
A59: = Class B Common Stock Market Capitalization | B59: 107.6162
A60: + Class C Common Stock Shares Out | B60: 0
A61: * Class C Common Stock Share Price | B61: 27.98
A62: = Class C Common Stock Market Capitalization | B62: 0
... A64: + Total Debt | B64: 18.025
A65: + Pref. Equity | B65: -
A66: + Total Minority Interest | B66: -
A67: - Long Term Marketable Securities | B67: -
A68: = Total Enterprise Value (TEV) | B68: 1962.6371
A70: Book Value of Common Equity | B70: 618.309
A71: + Pref. Equity | B71: -
A72: + Total Minority Interest | B72: -
A73: + Total Debt | B73: 18.025
A74: = Total Capital | B74: 636.334
A76: **For companies that have multiple share classes that publicly trade, we are incorporating the different prices to calculate our company level market capitalization. Please click on the value to see the detailed calculation. Prices shown on this page are the close price of the company’s primary stock class. Shares shown on this page are total company as-reported share values.
A79: Note: Striped area represents the impact of negative Net Liability on Market Cap.
A80: Total Liability includes Total Debt, Minority Interest and Pref. Equity.
A81: Net Liability includes Total Liability, net of Cash and Short Term Investments.
A82: TEV includes Market Cap and Net Liability.
A83: Total Capital includes Common Equity and Total Liability.
A85: Valuation Multiples based on Current Capitalization
A86: For the Fiscal Period Ending | B86: 12 months Dec-31-2025A | C86: LTM 12 months Jun-30-2026A | D86: 12 months Dec-31-2026E | E86: 12 months Dec-31-2027E | F86: 12 months Dec-31-2028E
A87: TEV/Total Revenue | B87: 4.440653 | C87: 3.991509 | D87: 3.557192 | E87: 2.9117545 | F87: 2.4110489
A89: TEV/EBITDA | B89: NM | C89: NM | D89: - | E89: 65.272848 | F89: 29.096252
A91: TEV/EBIT | B91: NM | C91: NM | D91: - | E91: - | F91: -
A93: P/Diluted EPS Before Extra | B93: NM | C93: NM | D93: - | E93: 65.098532 | F93: 35.13707
A95: P/BV | B95: 3.615879 | C95: 3.685557 | D95: 3.6840802 | E95: 3.4001784 | F95: 3.0359321
A97: Price/Tang BV | B97: 5.682983 | C97: 5.774732 | D97: - | E97: - | F97: -

Sheet Quarterly IS
A1: Income Statement
A2: For the Fiscal Period Ending | B2: 3 months Q1 Mar-31-2025 | C2: 3 months Q2 Jun-30-2025 | D2: 3 months Q3 Sep-30-2025 | E2: 3 months Q4 Dec-31-2025 | F2: 3 months Q1 Mar-31-2026 | G2: 3 months Q2 Jun-30-2026
A3: Currency | B3: USD | C3: USD | D3: USD | E3: USD | F3: USD | G3: USD
A5: Revenue | B5: 98.642 | C5: 107.133 | D5: 109.653 | E5: 118.909 | F5: 127.434 | G5: 135.707
A6: Other Revenue | B6: - | C6: - | D6: - | E6: - | F6: - | G6: -
A7: Total Revenue | B7: 98.642 | C7: 107.133 | D7: 109.653 | E7: 118.909 | F7: 127.434 | G7: 135.707
A9: Cost Of Goods Sold | B9: 58.832 | C9: 65.182 | D9: 66.567 | E9: 71.953 | F9: 77.379 | G9: 80.101
A10: Gross Profit | B10: 39.81 | C10: 41.951 | D10: 43.086 | E10: 46.956 | F10: 50.055 | G10: 55.606
A12: Selling General & Admin Exp. | B12: 35.688 | C12: 35.324 | D12: 38.846 | E12: 45.347 | F12: 49.111 | G12: 51.252
A13: R & D Exp. | B13: 21.346 | C13: 22.737 | D13: 23.131 | E13: 25.089 | F13: 24.528 | G13: 26.108
A14: Depreciation & Amort. | B14: - | C14: - | D14: - | E14: - | F14: - | G14: -
A15: Other Operating Expense/(Income) | B15: - | C15: - | D15: - | E15: 0.911 | F15: - | G15: -
A17: Other Operating Exp., Total | B17: 57.034 | C17: 58.061 | D17: 61.977 | E17: 71.347 | F17: 73.639 | G17: 77.36
A19: Operating Income | B19: -17.2 | C19: -16.1 | D19: -18.9 | E19: -24.4 | F19: -23.6 | G19: -21.8
A21: Interest Expense | B21: -2.4 | C21: -2.4 | D21: -2.1 | E21: -0.4 | F21: -0.2 | G21: -0.3
A22: Interest and Invest. Income | B22: 0.567 | C22: 0.487 | D22: 0.883 | E22: 3.335 | F22: 2.779 | G22: 2.799
A23: Net Interest Exp. | B23: -1.8 | C23: -1.9 | D23: -1.3 | E23: 2.964 | F23: 2.55 | G23: 2.517
A25: Currency Exchange Gains (Loss) | B25: 0.408 | C25: 0.661 | D25: -0.3 | E25: -0.3 | F25: -0.5 | G25: -0.3
A26: Other Non-Operating Inc. (Exp.) | B26: 1.299 | C26: -3 | D26: -5.4 | E26: -0.1 | F26: 0.135 | G26: 0.124
A27: EBT Excl. Unusual Items | B27: -17.4 | C27: -20.3 | D27: -25.9 | E27: -21.8 | F27: -21.4 | G27: -19.4
A29: Impairment of Goodwill | B29: - | C29: - | D29: - | E29: - | F29: - | G29: -
A30: Other Unusual Items | B30: 1.811 | C30: - | D30: -10.5 | E30: 0.231 | F30: 1.758 | G30: -
A31: EBT Incl. Unusual Items | B31: -15.5 | C31: -20.3 | D31: -36.4 | E31: -21.5 | F31: -19.6 | G31: -19.4
A33: Income Tax Expense | B33: 0.772 | C33: 0.872 | D33: 0.49 | E33: 0.387 | F33: 0.557 | G33: 0.165
A34: Earnings from Cont. Ops. | B34: -16.3 | C34: -21.2 | D34: -36.9 | E34: -21.9 | F34: -20.1 | G34: -19.6
A36: Earnings of Discontinued Ops. | B36: - | C36: - | D36: - | E36: - | F36: - | G36: -
A37: Extraord. Item & Account. Change | B37: - | C37: - | D37: - | E37: - | F37: - | G37: -
A38: Net Income to Company | B38: -16.3 | C38: -21.2 | D38: -36.9 | E38: -21.9 | F38: -20.1 | G38: -19.6
A40: Minority Int. in Earnings | B40: - | C40: - | D40: - | E40: - | F40: - | G40: -
A41: Net Income | B41: -16.3 | C41: -21.2 | D41: -36.9 | E41: -21.9 | F41: -20.1 | G41: -19.6
A43: Pref. Dividends and Other Adj. | B43: - | C43: - | D43: - | E43: - | F43: - | G43: -
A45: NI to Common Incl Extra Items | B45: -16.3 | C45: -21.2 | D45: -36.9 | E45: -21.9 | F45: -20.1 | G45: -19.6
A46: NI to Common Excl. Extra Items | B46: -16.3 | C46: -21.2 | D46: -36.9 | E46: -21.9 | F46: -20.1 | G46: -19.6
A48: Per Share Items
A49: Basic EPS | B49: -1.28 | C49: -1.66 | D49: -1.49 | E49: -0.27 | F49: -0.25 | G49: -0.24
A50: Basic EPS Excl. Extra Items | B50: -1.28 | C50: -1.66 | D50: -1.49 | E50: -0.27 | F50: -0.25 | G50: -0.24
A51: Weighted Avg. Basic Shares Out. | B51: 12.753056 | C51: 12.793403 | D51: 24.730353 | E51: 81.349711 | F51: 81.177074 | G51: 81.337205
A53: Diluted EPS | B53: -1.28 | C53: -1.66 | D53: -1.49 | E53: -0.27 | F53: -0.25 | G53: -0.24
A54: Diluted EPS Excl. Extra Items | B54: -1.28 | C54: -1.66 | D54: -1.49 | E54: -0.27 | F54: -0.25 | G54: -0.24
A55: Weighted Avg. Diluted Shares Out. | B55: 12.753056 | C55: 12.793403 | D55: 24.730353 | E55: 81.349711 | F55: 81.177074 | G55: 81.337205
A57: Normalized Basic EPS | B57: -0.85 | C57: -0.99 | D57: -0.65 | E57: -0.17 | F57: -0.16 | G57: -0.15
A58: Normalized Diluted EPS | B58: -0.85 | C58: -0.99 | D58: -0.65 | E58: -0.17 | F58: -0.16 | G58: -0.15
A60: Dividends per Share | B60: NA | C60: NA | D60: NA | E60: NA | F60: NA | G60: NA
A62: Supplemental Items
A63: EBITDA | B63: -14.9 | C63: -14 | D63: -16.8 | E63: -22.3 | F63: -21.2 | G63: -19.4
A64: EBITA | B64: -15.9 | C64: -15 | D64: -17.8 | E64: -23.3 | F64: -22.2 | G64: -20.4
A65: EBIT | B65: -17.2 | C65: -16.1 | D65: -18.9 | E65: -24.4 | F65: -23.6 | G65: -21.8
A66: Effective Tax Rate % | B66: NM | C66: NM | D66: NM | E66: NM | F66: NM | G66: NM
A67: Current Domestic Taxes | B67: NA | C67: NA | D67: NA | E67: 0.243 | F67: NA | G67: NA
A68: Current Foreign Taxes | B68: NA | C68: NA | D68: NA | E68: 1.685 | F68: NA | G68: NA
A69: Total Current Taxes | B69: - | C69: - | D69: - | E69: 1.928 | F69: - | G69: -
A70: Deferred Foreign Taxes | B70: NA | C70: NA | D70: NA | E70: 0.593 | F70: NA | G70: NA
A71: Total Deferred Taxes | B71: - | C71: - | D71: - | E71: 0.593 | F71: - | G71: -
A73: Normalized Net Income | B73: -10.8 | C73: -12.7 | D73: -16.2 | E73: -13.6 | F73: -13.3 | G73: -12.1
A74: Interest on Long Term Debt | B74: 2.406 | C74: 2.419 | D74: 2.147 | E74: NA | F74: 0.229 | G74: 0.282
A75: Filing Date | B75: 46154 | C75: 46240 | D75: 45975 | E75: 46087 | F75: 46154 | G75: 46240
A76: Restatement Type | B76: O | C76: NC | D76: O | E76: O | F76: O | G76: O
A77: Calculation Type | B77: REP | C77: REP | D77: REP | E77: Q4 | F77: REP | G77: REP
A79: Supplemental Operating Expense Items
A80: Selling and Marketing Exp. | B80: 15.202 | C80: 15.973 | D80: 17.657 | E80: 18.372 | F80: 20.49 | G80: 21.142
A81: General and Administrative Exp. | B81: 20.486 | C81: 19.351 | D81: 21.189 | E81: 26.975 | F81: 28.621 | G81: 30.11
A82: R&D Exp. | B82: 21.346 | C82: 22.737 | D82: 23.131 | E82: 25.138 | F82: 24.528 | G82: 26.108
A84: Stock-Based Comp., COGS | B84: 0.069 | C84: 0.037 | D84: 0.038 | E84: 0.056 | F84: 0.075 | G84: 0.098
A85: Stock-Based Comp., R&D Exp. | B85: 1.614 | C85: 1.549 | D85: 1.874 | E85: 3.54 | F85: 4.03 | G85: 4.302
A86: Stock-Based Comp., S&M Exp. | B86: 1.268 | C86: 1.271 | D86: 1.687 | E86: 2.895 | F86: 3.328 | G86: 3.623
A87: Stock-Based Comp., G&A Exp. | B87: 1.74 | C87: 1.805 | D87: 2.993 | E87: 7.905 | F87: 8.131 | G87: 7.987
A88: Stock-Based Comp., Total | B88: 4.691 | C88: 4.662 | D88: 6.592 | E88: 14.396 | F88: 15.564 | G88: 16.01
A91: Note: For multiple class companies, per share items are primary class equivalent, and for foreign companies listed as primary ADRs, per share items are ADR-equivalent.

Sheet BS
A1: Balance Sheet
A2: Balance Sheet as of: | B2: Q1 Mar-31-2025 | C2: Q2 Jun-30-2025 | D2: Q3 Sep-30-2025 | E2: Q4 Dec-31-2025 | F2: Q1 Mar-31-2026 | G2: Q2 Jun-30-2026
A3: Currency | B3: USD | C3: USD | D3: USD | E3: USD | F3: USD | G3: USD
A4: ASSETS
A5: Cash And Equivalents | B5: - | C5: 78.212 | D5: 378.158 | E5: 370.914 | F5: 348.158 | G5: 335.915
A6: Total Cash & ST Investments | B6: 77.905 | C6: 78.212 | D6: 378.158 | E6: 370.914 | F6: 348.158 | G6: 335.915
A8: Accounts Receivable | B8: - | C8: 82.228 | D8: 84.307 | E8: 81.572 | F8: 94.916 | G8: 104.679
A9: Total Receivables | B9: - | C9: 82.228 | D9: 84.307 | E9: 81.572 | F9: 94.916 | G9: 104.679
A11: Prepaid Exp. | B11: - | C11: 12.19 | D11: 15.641 | E11: 16.265 | F11: 17.204 | G11: 16.812
A12: Other Current Assets | B12: - | C12: 0.9 | D12: 0.8 | E12: 0.8 | F12: 0.9 | G12: 0.8
A13: Total Current Assets | B13: - | C13: 173.53 | D13: 478.906 | E13: 469.551 | F13: 461.178 | G13: 458.206
A15: Gross Property, Plant & Equipment | B15: - | C15: 44.389 | D15: 44.638 | E15: 47.997 | F15: 50.603 | G15: 51.203
A16: Accumulated Depreciation | B16: - | C16: -14.5 | D16: -15.4 | E16: -16.3 | F16: -17.1 | G16: -18.1
A17: Net Property, Plant & Equipment | B17: - | C17: 29.865 | D17: 29.254 | E17: 31.714 | F17: 33.459 | G17: 33.136
A19: Goodwill | B19: - | C19: 167.011 | D19: 165.962 | E19: 192.305 | F19: 191.005 | G19: 190.72
A20: Other Intangibles | B20: - | C20: 25.521 | D20: 24.127 | E20: 36.025 | F20: 34.336 | G20: 32.971
A21: Deferred Tax Assets, LT | B21: - | C21: 0.361 | D21: 1.183 | E21: 0.529 | F21: 0.437 | G21: 0.401
A22: Deferred Charges, LT | B22: - | C22: 0.8 | D22: 0.8 | E22: 0.7 | F22: 0.6 | G22: 0.6
... A24: Total Assets | B24: - | C24: 398.87 | D24: 702.058 | E24: 733.095 | F24: 723.32 | G24: 718.349
A26: LIABILITIES
A27: Accounts Payable | B27: - | C27: 6.9 | D27: 5.663 | E27: 4.427 | F27: 7.222 | G27: 6.039
A28: Accrued Exp. | B28: - | C28: 44.954 | D28: 50.169 | E28: 51.546 | F28: 47.694 | G28: 50.76
A29: Curr. Port. of Leases | B29: - | C29: 7.954 | D29: 8.106 | E29: 9.749 | F29: 10.021 | G29: 9.829
A30: Curr. Income Taxes Payable | B30: - | C30: 1.746 | D30: 1.345 | E30: 1.62 | F30: 1.733 | G30: 1.358
A31: Unearned Revenue, Current | B31: - | C31: 21.26 | D31: 24.103 | E31: 26.893 | F31: 23.954 | G31: 22.81
A32: Other Current Liabilities | B32: - | C32: - | D32: 3.319 | E32: - | F32: - | G32: -
A33: Total Current Liabilities | B33: - | C33: 82.814 | D33: 92.705 | E33: 94.235 | F33: 90.624 | G33: 90.796
A35: Long-Term Debt | B35: - | C35: 70.881 | D35: 25 | E35: - | F35: - | G35: -
A36: Long-Term Leases | B36: - | C36: 9.602 | D36: 8.409 | E36: 9.378 | F36: 9.249 | G36: 8.196
A37: Unearned Revenue, Non-Current | B37: - | C37: 1.499 | D37: 1.354 | E37: 1.746 | F37: 1.321 | G37: 1.048
A38: Other Non-Current Liabilities | B38: - | C38: 17.675 | D38: - | E38: - | F38: - | G38: -
A39: Total Liabilities | B39: - | C39: 182.471 | D39: 127.468 | E39: 105.359 | F39: 101.194 | G39: 100.04
A41: Pref. Stock, Convertible | B41: - | C41: 1220.005 | D41: - | E41: - | F41: - | G41: -
A42: Total Pref. Equity | B42: 1195.058 | C42: 1220.005 | D42: - | E42: - | F42: - | G42: -
A44: Common Stock | B44: - | C44: - | D44: 0.001 | E44: 0.001 | F44: 0.001 | G44: 0.001
A45: Additional Paid In Capital | B45: - | C45: 120.091 | D45: 1736.317 | E45: 1811.349 | F45: 1827.909 | G45: 1844.614
A46: Retained Earnings | B46: - | C46: -1132.5 | D46: -1169.4 | E46: -1191.3 | F46: -1211.5 | G46: -1231
A47: Treasury Stock | B47: - | C47: - | D47: - | E47: - | F47: - | G47: -
A48: Comprehensive Inc. and Other | B48: - | C48: 8.796 | D48: 7.652 | E48: 7.702 | F48: 5.681 | G48: 4.715
A49: Total Common Equity | B49: -987.1 | C49: -1003.6 | D49: 574.59 | E49: 627.736 | F49: 622.126 | G49: 618.309
A51: Total Equity | B51: 207.203 | C51: 216.399 | D51: 574.59 | E51: 627.736 | F51: 622.126 | G51: 618.309
A53: Total Liabilities And Equity | B53: - | C53: 398.87 | D53: 702.058 | E53: 733.095 | F53: 723.32 | G53: 718.349
A55: Supplemental Items
A56: Total Shares Out. on Filing Date | B56: 12.753056 | C56: 12.935746 | D56: 80.99082 | E56: 81.188814 | F56: 81.295871 | G56: 81.505613
A57: Total Shares Out. on Balance Sheet Date | B57: 12.753056 | C57: 12.935746 | D57: 79.588847 | E57: 81.122858 | F57: 81.261165 | G57: 81.444356
A58: Book Value/Share | B58: -77.65 | C58: -77.58 | D58: 7.22 | E58: 7.74 | F58: 7.66 | G58: 7.59
A59: Tangible Book Value | B59: -1173.6 | C59: -1196.1 | D59: 384.501 | E59: 399.406 | F59: 396.785 | G59: 394.618
A60: Tangible Book Value/Share | B60: -92.32 | C60: -92.47 | D60: 4.83 | E60: 4.92 | F60: 4.88 | G60: 4.85
A61: Total Debt | B61: 82.606 | C61: 88.437 | D61: 41.515 | E61: 19.127 | F61: 19.27 | G61: 18.025
A62: Net Debt | B62: 4.701 | C62: 10.225 | D62: -336.6 | E62: -351.8 | F62: -328.9 | G62: -317.9
A63: Total Minority Interest | B63: -0.8 | C63: NA | D63: NA | E63: NA | F63: NA | G63: NA
A64: Machinery | B64: NA | C64: 9.389 | D64: 9.513 | E64: 9.909 | F64: 10.062 | G64: 10.355
A65: Leasehold Improvements | B65: - | C65: 1.174 | D65: 1.254 | E65: 1.113 | F65: 1.113 | G65: 1.128
A66: Full Time Employees | B66: NA | C66: 973 | D66: NA | E66: 1040 | F66: NA | G66: NA
A67: Accum. Allowance for Doubtful Accts | B67: NA | C67: 0.01 | D67: 0.041 | E67: 0.024 | F67: 0.01 | G67: 0.02
A68: Filing Date | B68: NA | C68: 46240 | D68: 45975 | E68: 46087 | F68: 46154 | G68: 46240
A69: Restatement Type | B69: NV | C69: NC | D69: O | E69: O | F69: O | G69: O
A70: Calculation Type | B70: FWD | C70: RUP | D70: REP | E70: Q4 | F70: REP | G70: REP
A73: Note: For multiple class companies, total share counts are primary class equivalent, and for foreign companies listed as primary ADRs, total share counts are ADR-equivalent.

Sheet CFS
A1: Cash Flow
A2: For the Fiscal Period Ending | B2: 3 months Q1 Mar-31-2025 | C2: 3 months Q2 Jun-30-2025 | D2: 3 months Q3 Sep-30-2025 | E2: 3 months Q4 Dec-31-2025 | F2: 3 months Q1 Mar-31-2026 | G2: 3 months Q2 Jun-30-2026
A3: Currency | B3: USD | C3: USD | D3: USD | E3: USD | F3: USD | G3: USD
A5: Net Income | B5: -16.3 | C5: -21.2 | D5: -36.9 | E5: -21.9 | F5: -20.1 | G5: -19.6
A6: Depreciation & Amort. | B6: 0.983 | C6: 0.906 | D6: 1.014 | E6: 0.968 | F6: 0.987 | G6: 1
A7: Amort. of Goodwill and Intangibles | B7: 1.299 | C7: 1.155 | D7: 1.119 | E7: 1.085 | F7: 1.412 | G7: 1.38
A8: Depreciation & Amort., Total | B8: 2.282 | C8: 2.061 | D8: 2.133 | E8: 2.053 | F8: 2.399 | G8: 2.38
A10: Other Amortization | B10: 1.618 | C10: 1.71 | D10: 1.491 | E10: 0 | F10: - | G10: -
A11: Stock-Based Compensation | B11: 4.691 | C11: 4.662 | D11: 6.592 | E11: 14.396 | F11: 15.564 | G11: 16.01
A12: Other Operating Activities | B12: 0.708 | C12: 5.237 | D12: 17.7 | E12: 3.264 | F12: 3.376 | G12: 2.853
A13: Change in Acc. Receivable | B13: -0.5 | C13: -5.8 | D13: -2.1 | E13: 6.615 | F13: -13.8 | G13: -9.9
A14: Change in Acc. Payable | B14: 2.455 | C14: 0.365 | D14: -1.3 | E14: -1.9 | F14: 2.818 | G14: -1.2
A15: Change in Unearned Rev. | B15: -1 | C15: -1.6 | D15: 2.672 | E15: 0.272 | F15: -3.2 | G15: -1.4
A16: Change in Other Net Operating Assets | B16: 0.401 | C16: -1.7 | D16: 1.083 | E16: -3.2 | F16: -8.2 | G16: 0.073
A17: Cash from Ops. | B17: -5.6 | C17: -16.3 | D17: -8.5 | E17: -0.5 | F17: -21.2 | G17: -10.6
A19: Capital Expenditure | B19: -0.4 | C19: -0.6 | D19: -0.4 | E19: -0.3 | F19: -0.3 | G19: -0.4
A20: Cash Acquisitions | B20: - | C20: - | D20: - | E20: -39.9 | F20: - | G20: 0.279
A21: Divestitures | B21: - | C21: - | D21: - | E21: - | F21: - | G21: -
A22: Sale (Purchase) of Intangible assets | B22: -0.9 | C22: -1.2 | D22: -1.1 | E22: -1 | F22: -2 | G22: -2
A23: Invest. in Marketable & Equity Securt. | B23: - | C23: - | D23: - | E23: - | F23: - | G23: -
A24: Net (Inc.) Dec. in Loans Originated/Sold | B24: - | C24: - | D24: - | E24: - | F24: - | G24: -
A25: Other Investing Activities | B25: - | C25: - | D25: - | E25: - | F25: - | G25: -
A26: Cash from Investing | B26: -1.3 | C26: -1.8 | D26: -1.5 | E26: -41.2 | F26: -2.3 | G26: -2.1
A28: Short Term Debt Issued | B28: - | C28: - | D28: - | E28: - | F28: - | G28: -
A29: Long-Term Debt Issued | B29: 7.5 | C29: - | D29: - | E29: - | F29: - | G29: -
A30: Total Debt Issued | B30: 7.5 | C30: 0 | D30: 0 | E30: 0 | F30: - | G30: -
A31: Short Term Debt Repaid | B31: - | C31: - | D31: - | E31: - | F31: - | G31: -
A32: Long-Term Debt Repaid | B32: -5 | C32: - | D32: - | E32: - | F32: - | G32: -
A33: Total Debt Repaid | B33: -5 | C33: 0 | D33: -5 | E33: -25 | F33: - | G33: -
A35: Issuance of Common Stock | B35: 0.68 | C35: 1.374 | D35: 314.718 | E35: 63.388 | F35: 0.996 | G35: 0.695
A36: Issuance of Pref. Stock | B36: 20 | C36: 0 | D36: 0 | E36: 0 | F36: - | G36: -
A38: Total Dividends Paid | B38: - | C38: - | D38: - | E38: - | F38: - | G38: -
A40: Special Dividend Paid | B40: - | C40: - | D40: - | E40: - | F40: - | G40: -
A41: Other Financing Activities | B41: -0.3 | C41: 0 | D41: 0 | E41: -4 | F41: - | G41: -
A42: Cash from Financing | B42: 22.858 | C42: 1.374 | D42: 309.718 | E42: 34.376 | F42: 0.996 | G42: 0.695
A44: Foreign Exchange Rate Adj. | B44: 0.322 | C44: 0.743 | D44: 0.261 | E44: 0.119 | F44: -0.2 | G44: -0.1
A45: Net Change in Cash | B45: 16.324 | C45: -16 | D45: 299.991 | E45: -7.2 | F45: -22.7 | G45: -12.2
A47: Supplemental Items
A48: Cash Interest Paid | B48: 0.796 | C48: 0.642 | D48: 0.811 | E48: 0.529 | F48: NA | G48: 0.41
A49: Cash Taxes Paid | B49: 0.328 | C49: 0.59 | D49: 2.24 | E49: 0.26 | F49: 0.311 | G49: 0.483
A50: Levered Free Cash Flow | B50: NA | C50: NA | D50: -0.1 | E50: 1.61575 | F50: -17.5 | G50: -6.7
A51: Unlevered Free Cash Flow | B51: NA | C51: NA | D51: -0.2 | E51: 1.847625 | F51: -17.3 | G51: -6.5
A52: Change in Net Working Capital | B52: NA | C52: NA | D52: -4.3 | E52: -2 | F52: 18.266 | G52: 8.907
A53: Net Debt Issued | B53: 2.5 | C53: 0 | D53: -5 | E53: -25 | F53: NA | G53: NA
A54: Filing Date | B54: 46154 | C54: 46240 | D54: 45975 | E54: 46087 | F54: 46154 | G54: 46240
A55: Restatement Type | B55: O | C55: NC | D55: O | E55: O | F55: O | G55: O
A56: Calculation Type | B56: REP | C56: CFQ | D56: CFQ | E56: CFQ | F56: REP | G56: CFQ
